annaohero/__init__.py
annaohero/annaohero.py
tests/test.py
annaohero-0.0.1.dist-info/METADATA
annaohero-0.0.1.dist-info/WHEEL
annaohero-0.0.1.dist-info/top_level.txt
annaohero-0.0.1.dist-info/RECORD
