Metadata-Version: 2.1
Name: annaohero
Version: 0.0.1
Summary: Python module for writing scripts for for building multiple files into one file and vice versa 
Home-page: https://github.com/exitae337/annaohero
Author: AnnaOhero
Author-email: exitae337@gmail.com
License: UNKNOWN
Platform: UNKNOWN
